keycloakauth/__init__.py
keycloakauth/keycloak.py
keycloakauth-0.0.9.dist-info/LICENSE
keycloakauth-0.0.9.dist-info/METADATA
keycloakauth-0.0.9.dist-info/WHEEL
keycloakauth-0.0.9.dist-info/top_level.txt
keycloakauth-0.0.9.dist-info/RECORD
