Metadata-Version: 2.1
Name: keycloakauth
Version: 0.0.9
Summary: Custom Keycloak Worker
Home-page: https://bitbucket.org/VyacheslavKazakov/keycloak_auth/
Author: Vyacheslav Kazakov
Author-email: vyachka@gmail.com
License: MIT
Platform: UNKNOWN
Requires-Dist: django-keycloak-auth (==0.9.1)
Requires-Dist: requests (==2.24.0)
Requires-Dist: urllib3 (==1.25.11)
Provides-Extra: test
Requires-Dist: pytest ; extra == 'test'
Requires-Dist: pytest-cov ; extra == 'test'
Requires-Dist: requests-mock ; extra == 'test'
Requires-Dist: coverage ; extra == 'test'
Requires-Dist: pytest-flake8 ; extra == 'test'
